rcd/__init__.py
rcd/l_marvel/__init__.py
rcd/l_marvel/l_marvel.py
rcd/marvel/__init__.py
rcd/marvel/marvel.py
rcd/rol/__init__.py
rcd/rol/rol_hc.py
rcd/rsl/README.md
rcd/rsl/__init__.py
rcd/rsl/rsl_base.py
rcd/rsl/rsl_d.py
rcd/rsl/rsl_w.py
rcd/utilities/Independencies.py
rcd/utilities/ci_tests.py
rcd/utilities/data_graph_generation.py
rcd/utilities/utils.py
rcd-0.2.1.dist-info/METADATA
rcd-0.2.1.dist-info/WHEEL
rcd-0.2.1.dist-info/RECORD
