Metadata-Version: 2.1
Name: rcd
Version: 0.2.1
Summary: Recursive causal discovery framework
Author: sepehr78
Author-email: elahisepehr@gmail.com
Requires-Python: >=3.10,<4.0
Classifier: Programming Language :: Python :: 3
Classifier: Programming Language :: Python :: 3.10
Classifier: Programming Language :: Python :: 3.11
Classifier: Programming Language :: Python :: 3.12
Requires-Dist: networkx (>=3.4,<4.0)
Requires-Dist: numpy (>=2,<3)
Requires-Dist: pandas (>=2,<3)
Requires-Dist: scipy (>=1,<2)
Requires-Dist: tqdm (>=4,<5)
